{
  "one_time": false,
  "buttons": [
    [
      {
        "action": {
          "type": "text",
          "payload": "{\"button\": \"1\"}",
          "label": "АИТ"
        },
        "color": "secondary"
      }
    ],
    [
      {
        "action": {
          "type": "text",
          "payload": "{\"button\": \"1\"}",
          "label": "ПГС"
        },
        "color": "secondary"
      }
    ],
    [
      {
        "action": {
          "type": "text",
          "payload": "{\"button\": \"1\"}",
          "label": "ТС"
        },
        "color": "secondary"
      }
    ],
    [
      {
        "action": {
          "type": "text",
          "payload": "{\"button\": \"1\"}",
          "label": "УПЛ"
        },
        "color": "secondary"
      }
    ],
    [
      {
        "action": {
          "type": "text",
          "payload": "{\"button\": \"1\"}",
          "label": "ЭИМ"
        },
        "color": "secondary"
      }
    ],
    [
      {
        "action": {
          "type": "text",
          "payload": "{\"button\": \"1\"}",
          "label": "ФБФО"
        },
        "color": "secondary"
      }
    ],
    [
      {
        "action": {
          "type": "text",
          "payload": "{\"button\": \"2\"}",
          "label": "В главное меню"
        },
        "color": "secondary"
      }
    ]
  ]
}